ictools/__init__.py
ictools/auth.py
ictools/cli.py
ictools/hipchat.py
ictools/io.py
ictools/pagerduty.py
ictools-0.3.0.dist-info/DESCRIPTION.rst
ictools-0.3.0.dist-info/METADATA
ictools-0.3.0.dist-info/RECORD
ictools-0.3.0.dist-info/WHEEL
ictools-0.3.0.dist-info/entry_points.txt
ictools-0.3.0.dist-info/metadata.json
ictools-0.3.0.dist-info/top_level.txt
