Metadata-Version: 2.0
Name: ictools
Version: 0.3.0
Summary: Incident Commander Utilities
Home-page: https://github.com/dave-shawley/ictools
Author: Dave Shawley
Author-email: daves@aweber.com
License: UNKNOWN
Platform: any
Classifier: Intended Audience :: Developers
Classifier: License :: OSI Approved :: BSD License
Classifier: Operating System :: OS Independent
Classifier: Programming Language :: Python :: 3
Classifier: Development Status :: 4 - Beta
Requires-Dist: beautifulsoup4
Requires-Dist: maya
Requires-Dist: requests
